{"stats":{"minecraft:used":{"minecraft:peony":9,"minecraft:music_disc_far":1,"minecraft:smooth_quartz_slab":1241,"minecraft:dispenser":11,"minecraft:spruce_slab":2964,"minecraft:ladder":139,"minecraft:chest":129,"minecraft:stone":721,"minecraft:warped_sign":6,"minecraft:quartz_stairs":914,"minecraft:farmland":3,"minecraft:acacia_button":2,"minecraft:snowball":8,"minecraft:stripped_spruce_log":53,"minecraft:packed_ice":1,"minecraft:honey_block":23,"minecraft:netherite_shovel":273,"minecraft:lava_bucket":131,"minecraft:quartz_pillar":291,"minecraft:villager_spawn_egg":29,"minecraft:music_disc_pigstep":1,"minecraft:red_wool":158,"minecraft:black_stained_glass_pane":7,"minecraft:grass_block":5910,"minecraft:polished_andesite_stairs":465,"minecraft:quartz_block":4089,"minecraft:netherite_hoe":653,"minecraft:dark_oak_slab":14,"minecraft:dark_oak_button":30,"minecraft:stone_brick_stairs":267,"minecraft:dolphin_spawn_egg":3,"minecraft:red_stained_glass_pane":158,"minecraft:snow":506,"minecraft:bow":155,"minecraft:oak_sapling":2,"minecraft:furnace":9,"minecraft:acacia_fence":3,"minecraft:seagrass":33,"minecraft:light_blue_carpet":2,"minecraft:diorite":88,"minecraft:cow_spawn_egg":10,"minecraft:spruce_door":7,"minecraft:red_stained_glass":251,"minecraft:acacia_trapdoor":85,"minecraft:cactus":3,"minecraft:fox_spawn_egg":1,"minecraft:composter":9,"minecraft:parrot_spawn_egg":10,"minecraft:oak_leaves":54,"minecraft:golden_apple":13,"minecraft:dark_oak_trapdoor":22,"minecraft:sand":389,"minecraft:blast_furnace":12,"minecraft:chiseled_quartz_block":27,"minecraft:gray_concrete":85,"minecraft:black_concrete_powder":1,"minecraft:enderman_spawn_egg":1,"minecraft:crying_obsidian":91,"minecraft:birch_slab":33,"minecraft:polished_granite":41,"minecraft:oak_pressure_plate":33,"minecraft:diamond_ore":16,"minecraft:cat_spawn_egg":8,"minecraft:lilac":6,"minecraft:polished_andesite_slab":727,"minecraft:magenta_stained_glass_pane":10,"minecraft:diamond_sword":1877,"minecraft:dark_oak_fence":71,"minecraft:white_stained_glass":3,"minecraft:ice":887,"minecraft:oak_boat":8,"minecraft:gray_stained_glass":100,"minecraft:oak_trapdoor":39,"minecraft:iron_bars":632,"minecraft:enchanting_table":4,"minecraft:carved_pumpkin":48,"minecraft:red_concrete":837,"minecraft:armor_stand":15,"minecraft:wither_skeleton_spawn_egg":16,"minecraft:cooked_salmon":1,"minecraft:bee_spawn_egg":1,"minecraft:netherrack":219,"minecraft:torch":86,"minecraft:orange_bed":20,"minecraft:anvil":18,"minecraft:target":1,"minecraft:jungle_trapdoor":342,"minecraft:oak_fence_gate":12,"minecraft:polished_diorite":57,"minecraft:music_disc_mellohi":2,"minecraft:sea_lantern":506,"minecraft:spruce_button":8,"minecraft:iron_block":23,"minecraft:slime_block":175,"minecraft:warped_fence":25,"minecraft:spawner":33,"minecraft:jungle_log":1,"minecraft:chicken_spawn_egg":6,"minecraft:smooth_quartz":1715,"minecraft:totem_of_undying":2,"minecraft:prismarine_slab":38,"minecraft:barrel":55,"minecraft:bamboo":32,"minecraft:tripwire_hook":2,"minecraft:glowstone":839,"minecraft:iron_trapdoor":11,"minecraft:trapped_chest":22,"minecraft:crimson_pressure_plate":1,"minecraft:observer":130,"minecraft:wheat_seeds":327,"minecraft:water_bucket":2486,"minecraft:birch_planks":11,"minecraft:lime_wool":19,"minecraft:spruce_fence_gate":11,"minecraft:mossy_cobblestone":98,"minecraft:diamond_block":181,"minecraft:comparator":17,"minecraft:vine":85,"minecraft:oak_slab":2170,"minecraft:tnt":746,"minecraft:crafting_table":3,"minecraft:crimson_trapdoor":21,"minecraft:birch_sign":45,"minecraft:campfire":4,"minecraft:white_bed":15,"minecraft:spruce_log":2013,"minecraft:music_disc_strad":1,"minecraft:oak_log":2744,"minecraft:ender_eye":37,"minecraft:diamond_pickaxe":137,"minecraft:diamond_shovel":182,"minecraft:oak_button":4,"minecraft:pig_spawn_egg":5,"minecraft:spruce_trapdoor":40,"minecraft:spruce_sapling":3,"minecraft:music_disc_blocks":1,"minecraft:green_carpet":57,"minecraft:cobblestone":2515,"minecraft:acacia_pressure_plate":2,"minecraft:crimson_stairs":197,"minecraft:glass_pane":117,"minecraft:end_portal_frame":12,"minecraft:kelp":24,"minecraft:jukebox":4,"minecraft:light_blue_stained_glass_pane":19,"minecraft:red_sand":15,"minecraft:oak_sign":34,"minecraft:white_concrete_powder":6,"minecraft:shield":2,"minecraft:iron_sword":28,"minecraft:zombie_spawn_egg":100,"minecraft:bell":40,"minecraft:mossy_stone_brick_slab":4,"minecraft:stripped_crimson_stem":38,"minecraft:spruce_leaves":162,"minecraft:birch_pressure_plate":11,"minecraft:jungle_planks":46,"minecraft:carrot":37,"minecraft:music_disc_13":6,"minecraft:obsidian":1127,"minecraft:milk_bucket":2,"minecraft:glass":2824,"minecraft:crimson_button":16,"minecraft:coal_ore":1,"minecraft:quartz_slab":809,"minecraft:lantern":464,"minecraft:panda_spawn_egg":3,"minecraft:tropical_fish_spawn_egg":44,"minecraft:stone_bricks":41,"minecraft:item_frame":159,"minecraft:golden_sword":9,"minecraft:birch_trapdoor":21,"minecraft:repeater":346,"minecraft:redstone_lamp":536,"minecraft:scaffolding":10,"minecraft:jungle_button":2,"minecraft:beetroot_seeds":18,"minecraft:gold_block":27,"minecraft:fire_coral_fan":18,"minecraft:dark_oak_sapling":4,"minecraft:dark_oak_stairs":1,"minecraft:dropper":37,"minecraft:witch_spawn_egg":1,"minecraft:oak_planks":6562,"minecraft:redstone_block":425,"minecraft:diamond_axe":83,"minecraft:sugar_cane":16,"minecraft:white_wool":373,"minecraft:light_blue_wool":857,"minecraft:sponge":130,"minecraft:note_block":15,"minecraft:creeper_spawn_egg":41,"minecraft:redstone_torch":90,"minecraft:sticky_piston":299,"minecraft:lever":59,"minecraft:black_concrete":506,"minecraft:firework_rocket":9,"minecraft:acacia_door":2,"minecraft:daylight_detector":26,"minecraft:light_gray_concrete":74,"minecraft:heavy_weighted_pressure_plate":9,"minecraft:barrier":225,"minecraft:brown_wool":63,"minecraft:string":4,"minecraft:brown_stained_glass":18,"minecraft:warped_slab":44,"minecraft:gravel":15,"minecraft:iron_door":45,"minecraft:light_blue_concrete_powder":1,"minecraft:grindstone":19,"minecraft:andesite":2,"minecraft:chain":54,"minecraft:smooth_stone_slab":37,"minecraft:white_concrete":603,"minecraft:warped_button":11,"minecraft:bone_meal":40,"minecraft:cobweb":10,"minecraft:experience_bottle":461,"minecraft:oak_fence":1035,"minecraft:netherite_sword":754,"minecraft:jungle_leaves":69,"minecraft:petrified_oak_slab":240,"minecraft:trident":94,"minecraft:rose_bush":11,"minecraft:flint_and_steel":34,"minecraft:redstone":847,"minecraft:spruce_planks":3324,"minecraft:oak_door":47,"minecraft:dirt":798,"minecraft:white_carpet":696,"minecraft:hopper":492,"minecraft:spruce_stairs":561,"minecraft:warped_door":6,"minecraft:salmon_bucket":14,"minecraft:spruce_fence":1446,"minecraft:granite":2,"minecraft:light_blue_stained_glass":479,"minecraft:ravager_spawn_egg":9,"minecraft:stone_brick_slab":16,"minecraft:dark_oak_planks":1,"minecraft:bookshelf":12,"minecraft:yellow_stained_glass":28,"minecraft:oak_stairs":1680,"minecraft:crimson_slab":6,"minecraft:crimson_planks":190,"minecraft:light_gray_wool":1,"minecraft:golden_carrot":1,"minecraft:black_stained_glass":98,"minecraft:emerald_block":1,"minecraft:wolf_spawn_egg":1,"minecraft:lime_stained_glass":239,"minecraft:salmon_spawn_egg":16,"minecraft:netherite_pickaxe":2442,"minecraft:infested_cobblestone":191,"minecraft:cooked_beef":12,"minecraft:zombified_piglin_spawn_egg":12,"minecraft:turtle_egg":5,"minecraft:enchanted_golden_apple":18,"minecraft:turtle_spawn_egg":15,"minecraft:quartz_bricks":14,"minecraft:cooked_mutton":58,"minecraft:acacia_boat":5,"minecraft:cobblestone_stairs":168,"minecraft:snow_block":83,"minecraft:polished_andesite":5665,"minecraft:andesite_slab":66,"minecraft:birch_boat":16,"minecraft:magenta_stained_glass":246,"minecraft:beacon":9,"minecraft:vindicator_spawn_egg":49,"minecraft:cobblestone_slab":120,"minecraft:music_disc_cat":1,"minecraft:yellow_stained_glass_pane":52,"minecraft:polar_bear_spawn_egg":1,"minecraft:painting":21,"minecraft:warped_planks":274,"minecraft:smoker":36,"minecraft:dark_oak_door":39,"minecraft:piston":2,"minecraft:flower_pot":8,"minecraft:black_wool":37,"minecraft:command_block":1,"minecraft:netherite_axe":67,"minecraft:brown_stained_glass_pane":31,"minecraft:fishing_rod":3,"minecraft:end_crystal":24,"minecraft:white_banner":4,"minecraft:bucket":13,"minecraft:grass_path":4320,"minecraft:smooth_stone":9,"minecraft:birch_stairs":14},"minecraft:broken":{"minecraft:golden_sword":1},"minecraft:killed":{"minecraft:cave_spider":2,"minecraft:skeleton":16,"minecraft:guardian":1,"minecraft:chicken":2,"minecraft:magma_cube":4,"minecraft:parrot":8,"minecraft:salmon":2,"minecraft:iron_golem":1,"minecraft:pillager":2,"minecraft:zombie":414,"minecraft:cow":1,"minecraft:evoker":1,"minecraft:vindicator":46,"minecraft:horse":1,"minecraft:snow_golem":4,"minecraft:ravager":2,"minecraft:enderman":4,"minecraft:zombified_piglin":66,"minecraft:witch":6,"minecraft:spider":15,"minecraft:wither":1,"minecraft:silverfish":1,"minecraft:piglin_brute":1,"minecraft:wolf":8,"minecraft:piglin":8,"minecraft:zombie_villager":1,"minecraft:strider":1,"minecraft:creeper":44,"minecraft:stray":6,"minecraft:ghast":6,"minecraft:blaze":11,"minecraft:vex":5,"minecraft:squid":1,"minecraft:wither_skeleton":300,"minecraft:villager":11},"minecraft:picked_up":{"minecraft:anvil":4,"minecraft:prismarine_shard":5,"minecraft:oak_stairs":2,"minecraft:lead":1,"minecraft:diamond_sword":3,"minecraft:bee_spawn_egg":1,"minecraft:enchanted_book":5,"minecraft:golden_sword":2,"minecraft:music_disc_cat":1,"minecraft:string":75,"minecraft:dark_oak_trapdoor":1,"minecraft:shroomlight":1,"minecraft:beetroot":1,"minecraft:diamond_leggings":1,"minecraft:gold_nugget":161,"minecraft:spruce_planks":2,"minecraft:enchanted_golden_apple":859,"minecraft:dark_oak_door":2,"minecraft:music_disc_blocks":1,"minecraft:warped_button":2,"minecraft:stone_sword":4,"minecraft:carved_pumpkin":1,"minecraft:glowstone":18,"minecraft:wolf_spawn_egg":1,"minecraft:netherite_chestplate":5,"minecraft:iron_bars":1,"minecraft:snowball":193,"minecraft:sponge":1,"minecraft:cooked_beef":603,"minecraft:magma_block":63,"minecraft:barrier":1,"minecraft:feather":19,"minecraft:iron_door":1,"minecraft:birch_slab":15,"minecraft:water_bucket":3,"minecraft:jungle_log":30,"minecraft:flint":2,"minecraft:netherite_leggings":6,"minecraft:lantern":16,"minecraft:chiseled_polished_blackstone":1,"minecraft:stripped_spruce_log":2,"minecraft:ink_sac":2,"minecraft:dark_oak_log":4,"minecraft:quartz_bricks":2,"minecraft:polished_andesite":3,"minecraft:dispenser":2,"minecraft:lever":7,"minecraft:granite":4,"minecraft:spruce_button":1,"minecraft:crimson_roots":1,"minecraft:spruce_leaves":1,"minecraft:redstone_lamp":1,"minecraft:elytra":4,"minecraft:flint_and_steel":1,"minecraft:snow":4,"minecraft:white_carpet":27,"minecraft:netherite_sword":7,"minecraft:poppy":17,"minecraft:spruce_slab":1,"minecraft:quartz_stairs":2,"minecraft:chest":1,"minecraft:egg":39,"minecraft:sandstone":35,"minecraft:oak_door":1,"minecraft:music_disc_mellohi":2,"minecraft:spruce_fence":7,"minecraft:fire_charge":143,"minecraft:carrot":48,"minecraft:redstone":104,"minecraft:netherite_pickaxe":1,"minecraft:prismarine_crystals":59,"minecraft:tnt":4,"minecraft:beetroot_seeds":1,"minecraft:warped_sign":1,"minecraft:totem_of_undying":5,"minecraft:gold_ingot":4,"minecraft:rail":16,"minecraft:oak_log":3,"minecraft:jungle_button":2,"minecraft:paper":155,"minecraft:white_banner":3,"minecraft:music_disc_far":1,"minecraft:iron_ore":73,"minecraft:iron_sword":1,"minecraft:dark_oak_slab":1,"minecraft:gravel":44,"minecraft:spruce_sapling":1,"minecraft:sea_lantern":2,"minecraft:firework_rocket":1630,"minecraft:diamond_shovel":1,"minecraft:redstone_ore":6,"minecraft:painting":1,"minecraft:melon_seeds":1,"minecraft:hopper":1,"minecraft:ender_pearl":3,"minecraft:music_disc_strad":1,"minecraft:wheat":2,"minecraft:potion":1,"minecraft:sticky_piston":1,"minecraft:experience_bottle":32,"minecraft:red_sand":2,"minecraft:bucket":1,"minecraft:redstone_torch":10,"minecraft:cobblestone_slab":1,"minecraft:ender_eye":11,"minecraft:tipped_arrow":3,"minecraft:stick":4,"minecraft:oak_fence":24,"minecraft:torch":119,"minecraft:snow_block":3,"minecraft:porkchop":1,"minecraft:netherite_shovel":2,"minecraft:diorite":45,"minecraft:quartz_block":50,"minecraft:nether_gold_ore":11,"minecraft:rotten_flesh":408,"minecraft:obsidian":6,"minecraft:cod":2,"minecraft:cobblestone":446,"minecraft:magma_cream":2,"minecraft:repeater":11,"minecraft:andesite":1,"minecraft:potato":1,"minecraft:warped_trapdoor":1,"minecraft:prismarine_bricks":1,"minecraft:acacia_boat":4,"minecraft:wither_skeleton_skull":3,"minecraft:lapis_lazuli":25,"minecraft:dirt":419,"minecraft:name_tag":1,"minecraft:bone":85,"minecraft:bow":3,"minecraft:wheat_seeds":48,"minecraft:netherite_axe":1,"minecraft:bamboo":1,"minecraft:oak_planks":31,"minecraft:music_disc_13":4,"minecraft:sand":72,"minecraft:grass_block":48,"minecraft:spectral_arrow":436,"minecraft:mossy_cobblestone":1,"minecraft:dark_prismarine":51,"minecraft:jungle_leaves":2,"minecraft:clay":4,"minecraft:netherite_helmet":5,"minecraft:soul_lantern":1,"minecraft:cracked_polished_blackstone_bricks":8,"minecraft:golden_apple":8,"minecraft:emerald":62,"minecraft:netherrack":833,"minecraft:oak_leaves":8,"minecraft:nether_star":1,"minecraft:chicken":1,"minecraft:ladder":6,"minecraft:packed_ice":10,"minecraft:gold_block":10,"minecraft:shield":3,"minecraft:iron_axe":9,"minecraft:item_frame":1,"minecraft:detector_rail":3,"minecraft:oak_boat":3,"minecraft:end_stone":2,"minecraft:stone_button":2,"minecraft:trident":2,"minecraft:dark_oak_planks":34,"minecraft:weeping_vines":10,"minecraft:arrow":35,"minecraft:saddle":2,"minecraft:netherite_boots":7,"minecraft:dark_oak_button":2,"minecraft:cut_sandstone":4,"minecraft:birch_planks":14,"minecraft:ice":1,"minecraft:gunpowder":41,"minecraft:cobblestone_stairs":1,"minecraft:orange_terracotta":1,"minecraft:red_carpet":30,"minecraft:cooked_chicken":1,"minecraft:soul_sand":27,"minecraft:nether_quartz_ore":6,"minecraft:birch_boat":1,"minecraft:dandelion":1,"minecraft:grass_path":4,"minecraft:gold_ore":22,"minecraft:green_carpet":10,"minecraft:spider_eye":6,"minecraft:netherite_hoe":2,"minecraft:coal":158},"minecraft:killed_by":{"minecraft:ravager":2,"minecraft:vindicator":4,"minecraft:wolf":1,"minecraft:ender_dragon":5,"minecraft:wither_skeleton":1,"minecraft:player":3,"minecraft:spider":1,"minecraft:enderman":3},"minecraft:dropped":{"minecraft:clay":4,"minecraft:iron_sword":3,"minecraft:oak_pressure_plate":3,"minecraft:lapis_lazuli":1,"minecraft:cooked_beef":91,"minecraft:diamond":60,"minecraft:crafting_table":1,"minecraft:cooked_porkchop":2,"minecraft:dark_oak_slab":1,"minecraft:weeping_vines":5,"minecraft:dark_oak_button":5,"minecraft:saddle":2,"minecraft:quartz_pillar":1,"minecraft:elytra":1,"minecraft:red_mushroom":1,"minecraft:red_carpet":1,"minecraft:item_frame":6,"minecraft:emerald":5,"minecraft:gold_block":4,"minecraft:dirt":159,"minecraft:dark_oak_trapdoor":2,"minecraft:chain":1,"minecraft:gold_nugget":19,"minecraft:bone_meal":1,"minecraft:sand":68,"minecraft:white_wool":2,"minecraft:end_crystal":2,"minecraft:bone":26,"minecraft:oak_door":2,"minecraft:emerald_block":1,"minecraft:dark_oak_door":2,"minecraft:note_block":65,"minecraft:sugar_cane":1,"minecraft:lever":15,"minecraft:diamond_block":5,"minecraft:detector_rail":3,"minecraft:wheat":1,"minecraft:netherite_sword":15,"minecraft:birch_sapling":1,"minecraft:obsidian":11,"minecraft:rotten_flesh":111,"minecraft:oak_planks":7,"minecraft:enchanted_golden_apple":251,"minecraft:netherite_shovel":1,"minecraft:warped_sign":2,"minecraft:quartz_bricks":1,"minecraft:jungle_trapdoor":70,"minecraft:azure_bluet":1,"minecraft:acacia_button":1,"minecraft:sea_lantern":5,"minecraft:tipped_arrow":2,"minecraft:quartz_block":66,"minecraft:hopper":8,"minecraft:ladder":9,"minecraft:spruce_slab":17,"minecraft:glass":6,"minecraft:beef":64,"minecraft:crying_obsidian":1,"minecraft:stone_brick_stairs":3,"minecraft:egg":2,"minecraft:crimson_planks":3,"minecraft:enchanted_book":14,"minecraft:iron_ingot":2,"minecraft:netherite_pickaxe":1,"minecraft:wheat_seeds":74,"minecraft:clock":1,"minecraft:tnt":67,"minecraft:netherite_helmet":1,"minecraft:netherite_chestplate":1,"minecraft:oak_fence":23,"minecraft:feather":3,"minecraft:barrier":132,"minecraft:cobblestone":44,"minecraft:granite":4,"minecraft:spruce_button":2,"minecraft:command_block":1,"minecraft:red_stained_glass":1,"minecraft:coal":4,"minecraft:golden_apple":58,"minecraft:polished_andesite":15,"minecraft:warped_trapdoor":65,"minecraft:lava_bucket":7,"minecraft:cobweb":1,"minecraft:crimson_stairs":4,"minecraft:iron_trapdoor":1,"minecraft:sponge":120,"minecraft:ink_sac":2,"minecraft:rose_bush":2,"minecraft:cooked_salmon":64,"minecraft:diamond_helmet":1,"minecraft:dried_kelp":1,"minecraft:oak_stairs":6,"minecraft:smooth_stone":1,"minecraft:iron_shovel":1,"minecraft:paper":267,"minecraft:string":23,"minecraft:lily_pad":1,"minecraft:spruce_sapling":1,"minecraft:pink_tulip":2,"minecraft:snow_block":1,"minecraft:zombie_spawn_egg":1,"minecraft:netherite_hoe":1,"minecraft:smooth_stone_slab":1,"minecraft:bowl":1,"minecraft:sticky_piston":12,"minecraft:grass_path":18,"minecraft:chicken":1,"minecraft:white_carpet":25,"minecraft:slime_block":3,"minecraft:light_gray_concrete":2,"minecraft:diamond_ore":1,"minecraft:oak_sign":5,"minecraft:spruce_fence":14,"minecraft:lily_of_the_valley":1,"minecraft:diamond_sword":3,"minecraft:cobblestone_slab":2,"minecraft:stone":10,"minecraft:crimson_slab":1,"minecraft:peony":1,"minecraft:spruce_trapdoor":2,"minecraft:spruce_planks":13,"minecraft:diamond_pickaxe":1,"minecraft:light_blue_carpet":1,"minecraft:andesite_stairs":1,"minecraft:carved_pumpkin":1,"minecraft:redstone_torch":15,"minecraft:warped_button":5,"minecraft:spider_eye":128,"minecraft:barrel":1,"minecraft:sandstone":33,"minecraft:birch_boat":3,"minecraft:red_sand":2,"minecraft:bow":2,"minecraft:bell":1,"minecraft:magma_block":64,"minecraft:quartz_slab":2,"minecraft:daylight_detector":1,"minecraft:soul_sand":20,"minecraft:birch_planks":3,"minecraft:dark_oak_stairs":1,"minecraft:diamond_axe":2,"minecraft:warped_fungus":1,"minecraft:oak_log":14,"minecraft:lantern":9,"minecraft:jungle_planks":63,"minecraft:red_wool":2,"minecraft:carrot_on_a_stick":2,"minecraft:birch_slab":2,"minecraft:cobblestone_stairs":4,"minecraft:cod":64,"minecraft:music_disc_13":1,"minecraft:flint":1,"minecraft:spruce_leaves":3,"minecraft:cracked_polished_blackstone_bricks":8,"minecraft:redstone_lamp":5,"minecraft:packed_ice":9,"minecraft:ice":5,"minecraft:dispenser":6,"minecraft:crimson_roots":1,"minecraft:seagrass":1,"minecraft:cut_sandstone":4,"minecraft:snowball":113,"minecraft:prismarine_brick_slab":1,"minecraft:acacia_door":1,"minecraft:gold_ingot":1,"minecraft:armor_stand":1,"minecraft:gravel":13,"minecraft:white_tulip":1,"minecraft:chiseled_polished_blackstone":1,"minecraft:crimson_fungus":1,"minecraft:pig_spawn_egg":2,"minecraft:andesite_slab":1,"minecraft:diamond_shovel":1,"minecraft:cooked_mutton":65,"minecraft:poppy":14,"minecraft:oak_fence_gate":2,"minecraft:turtle_helmet":1,"minecraft:gunpowder":14,"minecraft:trident":1,"minecraft:petrified_oak_slab":1,"minecraft:dropper":7,"minecraft:melon_seeds":1,"minecraft:glowstone":10,"minecraft:chest":3,"minecraft:iron_bars":3,"minecraft:arrow":14,"minecraft:oak_leaves":4,"minecraft:polished_granite":2,"minecraft:netherrack":396,"minecraft:firework_rocket":458,"minecraft:water_bucket":11,"minecraft:stripped_spruce_log":3,"minecraft:oak_slab":4,"minecraft:lilac":1,"minecraft:diamond_leggings":2,"minecraft:poisonous_potato":128,"minecraft:netherite_axe":1,"minecraft:spectral_arrow":65,"minecraft:observer":7,"minecraft:activator_rail":4,"minecraft:spruce_stairs":2,"minecraft:grass_block":26,"minecraft:stick":1,"minecraft:spruce_fence_gate":1,"minecraft:iron_block":1,"minecraft:nether_gold_ore":5,"minecraft:torch":29,"minecraft:repeater":18,"minecraft:white_concrete":3,"minecraft:smooth_quartz":2,"minecraft:brown_wool":1,"minecraft:iron_door":12,"minecraft:fire_charge":64,"minecraft:green_carpet":12,"minecraft:smooth_quartz_slab":3,"minecraft:music_disc_strad":1,"minecraft:jungle_leaves":1,"minecraft:polished_andesite_stairs":1,"minecraft:iron_axe":4,"minecraft:orange_bed":1,"minecraft:light_blue_stained_glass_pane":1,"minecraft:redstone_block":8,"minecraft:redstone":38,"minecraft:red_concrete":3,"minecraft:polished_diorite":1,"minecraft:farmland":2,"minecraft:anvil":4,"minecraft:oak_trapdoor":1,"minecraft:jukebox":2,"minecraft:comparator":7,"minecraft:villager_spawn_egg":1,"minecraft:ender_eye":52,"minecraft:warped_door":1,"minecraft:flint_and_steel":4,"minecraft:crimson_button":1,"minecraft:snow":24,"minecraft:shield":1,"minecraft:oak_button":1,"minecraft:diamond_chestplate":2,"minecraft:orange_terracotta":1,"minecraft:andesite":1,"minecraft:fox_spawn_egg":1,"minecraft:cake":1,"minecraft:quartz_stairs":11,"minecraft:oak_boat":2,"minecraft:oak_sapling":1,"minecraft:golden_sword":1,"minecraft:birch_sign":2,"minecraft:cow_spawn_egg":1,"minecraft:diamond_boots":2,"minecraft:spruce_log":7,"minecraft:beacon":2,"minecraft:nether_quartz_ore":3},"minecraft:mined":{"minecraft:dark_oak_planks":21,"minecraft:jungle_leaves":21,"minecraft:obsidian":6,"minecraft:granite":9,"minecraft:chiseled_polished_blackstone":1,"minecraft:jungle_log":40,"minecraft:nether_wart":10,"minecraft:spawner":2,"minecraft:weeping_vines_plant":4,"minecraft:magma_block":148,"minecraft:fire":2,"minecraft:oak_stairs":2,"minecraft:cut_sandstone":22,"minecraft:soul_fire":2,"minecraft:torch":14,"minecraft:grass":13,"minecraft:dark_prismarine":31,"minecraft:dark_oak_log":5,"minecraft:sea_lantern":14,"minecraft:end_stone":3,"minecraft:nether_bricks":3,"minecraft:spruce_fence":2,"minecraft:crimson_roots":1,"minecraft:redstone_ore":14,"minecraft:snow":4,"minecraft:andesite":23,"minecraft:vine":5,"minecraft:rail":2,"minecraft:glass_pane":2,"minecraft:soul_sand":11,"minecraft:sponge":1,"minecraft:diorite":16,"minecraft:gravel":18,"minecraft:cobweb":12,"minecraft:stone_bricks":1,"minecraft:gold_ore":22,"minecraft:farmland":1,"minecraft:grass_block":51,"minecraft:cracked_polished_blackstone_bricks":2,"minecraft:sandstone_stairs":1,"minecraft:iron_ore":77,"minecraft:blackstone":6,"minecraft:orange_terracotta":2,"minecraft:nether_quartz_ore":1,"minecraft:prismarine":10,"minecraft:oak_planks":21,"minecraft:wall_torch":12,"minecraft:blue_terracotta":1,"minecraft:dark_oak_door":1,"minecraft:tnt":9,"minecraft:sand":125,"minecraft:dirt":85,"minecraft:netherrack":1654,"minecraft:oak_leaves":15,"minecraft:nether_gold_ore":27,"minecraft:diamond_ore":1,"minecraft:red_carpet":1,"minecraft:weeping_vines":3,"minecraft:birch_slab":20,"minecraft:sandstone":36,"minecraft:gold_block":8,"minecraft:nether_brick_fence":4,"minecraft:shroomlight":1,"minecraft:packed_ice":12,"minecraft:wet_sponge":2,"minecraft:stone":279,"minecraft:snow_block":1,"minecraft:basalt":2,"minecraft:oak_fence":2,"minecraft:lapis_ore":1,"minecraft:prismarine_bricks":22,"minecraft:birch_planks":7,"minecraft:coal_ore":87,"minecraft:cracked_stone_bricks":1},"minecraft:custom":{"minecraft:interact_with_crafting_table":5,"minecraft:open_barrel":23,"minecraft:bell_ring":115,"minecraft:leave_game":235,"minecraft:time_since_death":560590,"minecraft:damage_blocked_by_shield":140,"minecraft:deaths":25,"minecraft:jump":16013,"minecraft:enchant_item":8,"minecraft:interact_with_furnace":3,"minecraft:play_record":13,"minecraft:traded_with_villager":13,"minecraft:sleep_in_bed":8,"minecraft:damage_dealt":114284,"minecraft:interact_with_smoker":7,"minecraft:inspect_dispenser":17,"minecraft:horse_one_cm":21341,"minecraft:inspect_dropper":99,"minecraft:interact_with_anvil":87,"minecraft:inspect_hopper":54,"minecraft:sneak_time":84569,"minecraft:interact_with_blast_furnace":42,"minecraft:tune_noteblock":138,"minecraft:time_since_rest":186086,"minecraft:swim_one_cm":113789,"minecraft:fly_one_cm":15680685,"minecraft:open_chest":285,"minecraft:fish_caught":1,"minecraft:fall_one_cm":162207,"minecraft:animals_bred":8,"minecraft:damage_resisted":998,"minecraft:sprint_one_cm":2547112,"minecraft:drop":2284,"minecraft:talked_to_villager":12,"minecraft:walk_on_water_one_cm":594320,"minecraft:play_one_minute":3605991,"minecraft:interact_with_beacon":5,"minecraft:player_kills":4,"minecraft:crouch_one_cm":112242,"minecraft:mob_kills":1213,"minecraft:climb_one_cm":69792,"minecraft:walk_one_cm":8422217,"minecraft:walk_under_water_one_cm":306336,"minecraft:boat_one_cm":536464,"minecraft:raid_trigger":1,"minecraft:pot_flower":8,"minecraft:interact_with_grindstone":3,"minecraft:damage_taken":11636,"minecraft:damage_absorbed":1615,"minecraft:trigger_trapped_chest":51,"minecraft:pig_one_cm":20900,"minecraft:aviate_one_cm":1812863},"minecraft:crafted":{"minecraft:gold_ingot":17,"minecraft:firework_star":1,"minecraft:iron_ingot":64,"minecraft:iron_axe":10,"minecraft:iron_sword":3,"minecraft:jungle_planks":116,"minecraft:firework_rocket":3}},"DataVersion":2586}